next_word_prediction/__init__.py
next_word_prediction/model.py
next_word_prediction-0.2.0.dist-info/LICENSE
next_word_prediction-0.2.0.dist-info/METADATA
next_word_prediction-0.2.0.dist-info/WHEEL
next_word_prediction-0.2.0.dist-info/top_level.txt
next_word_prediction-0.2.0.dist-info/RECORD
