Metadata-Version: 2.1
Name: next-word-prediction
Version: 0.2.0
Summary: Generative Pretrained Transformer 2 (GPT-2) for Language Modeling using the PyTorch-Transformers library.
Home-page: https://github.com/rdgozum/Next-Word-Prediction
Author: Ryan Paul Gozum
Author-email: ryanpaul.gozum@gmail.com
License: MIT
Keywords: language model
Platform: UNKNOWN
Classifier: License :: OSI Approved :: MIT License
Classifier: Programming Language :: Python :: 3.6
Classifier: Programming Language :: Python :: 3.7
Classifier: Programming Language :: Python :: 3.8
